host_api/.deta/prog_info
host_api/.deta/state
host_api/__init__.py
host_api/__main__.py
host_api/main.py
host_api/requirements.txt
host.api-0.1.0.dist-info/entry_points.txt
host.api-0.1.0.dist-info/WHEEL
host.api-0.1.0.dist-info/METADATA
host.api-0.1.0.dist-info/RECORD
