Metadata-Version: 2.1
Name: host.api
Version: 0.1.0
Summary: 
Author: Your Name
Author-email: you@example.com
Requires-Python: >=3.7,<4.0
Classifier: Programming Language :: Python :: 3
Classifier: Programming Language :: Python :: 3.7
Classifier: Programming Language :: Python :: 3.8
Classifier: Programming Language :: Python :: 3.9
Requires-Dist: bcrypt (>=3.2.0,<4.0.0)
Requires-Dist: deta (>=0.7,<0.8)
Requires-Dist: fastapi (>=0.63.0,<0.64.0)
Requires-Dist: passlib (>=1.7.4,<2.0.0)
Requires-Dist: python-dotenv (>=0.15.0,<0.16.0)
Requires-Dist: python-jose (>=3.2.0,<4.0.0)
Requires-Dist: typer (>=0.3.2,<0.4.0)
Requires-Dist: uvicorn (>=0.13.3,<0.14.0)
